README.md
setup.py
allure_pytest_master/Base.py
allure_pytest_master/VerifyAction.py
allure_pytest_master/__init__.py
allure_pytest_master/handle_api.py
allure_pytest_master/verify_common.py
allure_pytest_master.egg-info/PKG-INFO
allure_pytest_master.egg-info/SOURCES.txt
allure_pytest_master.egg-info/dependency_links.txt
allure_pytest_master.egg-info/top_level.txt