Metadata-Version: 2.1
Name: allure-pytest-master
Version: 0.0.7
Summary: A allure and pytest used package
Home-page: https://www.baidu.com/
Author: jar yuan
Author-email: author@example.com
License: UNKNOWN
Platform: UNKNOWN
Classifier: Programming Language :: Python :: 3
Classifier: License :: OSI Approved :: MIT License
Classifier: Operating System :: OS Independent
